nmdc_schema/README.md
nmdc_schema/__init__.py
nmdc_schema/anyuri_strings_to_iris.py
nmdc_schema/dump_single_modality.py
nmdc_schema/get_json_schema.py
nmdc_schema/get_nmdc_view.py
nmdc_schema/gold-to-mixs.sssom.tsv
nmdc_schema/id_helpers.py
nmdc_schema/migration_recursion.py
nmdc_schema/migrators/.docker/.env.example
nmdc_schema/migrators/.docker/docker-compose.yaml
nmdc_schema/migrators/.docker/mongoKeyFile
nmdc_schema/migrators/.docker/mongo_init/initialize_replica_set.sh
nmdc_schema/migrators/.docker/wait-for-it.sh
nmdc_schema/migrators/README.md
nmdc_schema/migrators/__init__.py
nmdc_schema/migrators/adapters/adapter_base.py
nmdc_schema/migrators/adapters/dictionary_adapter.py
nmdc_schema/migrators/adapters/mongo_adapter.py
nmdc_schema/migrators/adapters/test_dictionary_adapter.py
nmdc_schema/migrators/adapters/test_mongo_adapter.py
nmdc_schema/migrators/assets/migrator_from_10_2_0_to_11_0_0_part_08/instrument_set.yaml
nmdc_schema/migrators/assets/migrator_from_11_7_to_11_8/data_category_map.yaml
nmdc_schema/migrators/assets/migrator_from_8_1_to_9_0/study_dois_changes.yaml
nmdc_schema/migrators/assets/migrator_from_9_1_to_9_2/websites_dois.yaml
nmdc_schema/migrators/cli/README.md
nmdc_schema/migrators/cli/__init__.py
nmdc_schema/migrators/cli/create_migrator.py
nmdc_schema/migrators/cli/migrator.py.template
nmdc_schema/migrators/cli/run_migrator.py
nmdc_schema/migrators/helpers.py
nmdc_schema/migrators/migration_reporter.py
nmdc_schema/migrators/migrator_base.py
nmdc_schema/migrators/migrator_from_10_0_0_to_10_1_2.py
nmdc_schema/migrators/migrator_from_10_2_0_to_11_0_0.py
nmdc_schema/migrators/migrator_from_10_3_0_to_10_4_0.py
nmdc_schema/migrators/migrator_from_10_4_0_to_10_5_4.py
nmdc_schema/migrators/migrator_from_10_5_4_to_10_5_5.py
nmdc_schema/migrators/migrator_from_10_5_5_to_10_5_6.py
nmdc_schema/migrators/migrator_from_10_5_6_to_10_6_0.py
nmdc_schema/migrators/migrator_from_10_6_0_to_10_7_0.py
nmdc_schema/migrators/migrator_from_11_0_3_to_11_1_0.py
nmdc_schema-11.15.1.dist-info/METADATA
nmdc_schema-11.15.1.dist-info/WHEEL
nmdc_schema-11.15.1.dist-info/entry_points.txt
nmdc_schema-11.15.1.dist-info/licenses/LICENSE
nmdc_schema-11.15.1.dist-info/RECORD
