Metadata-Version: 2.4
Name: nmdc_schema
Version: 11.15.1
Summary: Schema resources for the National Microbiome Data Collaborative (NMDC)
License: MIT
License-File: LICENSE
Keywords: NMDC,schema,metadata,microbiome
Author: Bill Duncan
Author-email: wdduncan@gmail.com
Requires-Python: >=3.10,<4.0
Classifier: Development Status :: 5 - Production/Stable
Classifier: Intended Audience :: Developers
Classifier: Intended Audience :: Science/Research
Classifier: License :: OSI Approved :: MIT License
Classifier: Programming Language :: Python :: 3
Classifier: Programming Language :: Python :: 3.10
Classifier: Programming Language :: Python :: 3.11
Classifier: Programming Language :: Python :: 3.12
Classifier: Programming Language :: Python :: 3.13
Classifier: Programming Language :: Python :: 3.14
Classifier: Programming Language :: Python :: 3 :: Only
Requires-Dist: click (>=8,<9)
Requires-Dist: click-log (>=0.4.0,<0.5.0)
Requires-Dist: curies (>=0.9.0,<0.10.0)
Requires-Dist: deprecated (>=1,<2)
Requires-Dist: jsonasobj2 (>=1,<2)
Requires-Dist: jsonschema (>=4,<5)
Requires-Dist: linkml (>=1.9.6,<2.0.0)
Requires-Dist: linkml-runtime (>=1.9.5,<2.0.0)
Requires-Dist: pyasn1 (>=0.6.2)
Requires-Dist: pymdown-extensions (>=10.16.1)
Requires-Dist: pymongo (>=4.7.2,<5.0.0)
Requires-Dist: python-dotenv
Requires-Dist: pyyaml (>=6,<7)
Requires-Dist: rdflib (>=6.2.0,<7.0.0)
Requires-Dist: requests (>=2,<3)
Requires-Dist: urllib3 (>=2.6.0)
Project-URL: Documentation, https://microbiomedata.github.io/nmdc-schema/
Project-URL: Homepage, https://microbiomedata.github.io/nmdc-schema/
Project-URL: Repository, https://github.com/microbiomedata/nmdc-schema
